pydolphin/__init__.py
pydolphin/schedule.py
pydolphin/utils/__init__.py
pydolphin/utils/get_host.py
pydolphin/utils/main_ping.py
pydolphin-0.1.2.dist-info/LICENSE
pydolphin-0.1.2.dist-info/METADATA
pydolphin-0.1.2.dist-info/WHEEL
pydolphin-0.1.2.dist-info/top_level.txt
pydolphin-0.1.2.dist-info/RECORD
