Metadata-Version: 2.1
Name: pydolphin
Version: 0.1.2
Summary: a convenient solution to heroku web apps / APIs.
Home-page: https://github.com/dolphinorg/dolphin
Author: Dhruv Maaniya (@midnightmadwalk)
Author-email: midnightmadwalk@gmail.com
License: MIT
Platform: UNKNOWN
Classifier: Programming Language :: Python :: 3
Classifier: License :: OSI Approved :: MIT License
Classifier: Operating System :: OS Independent
Requires-Python: >=3.6
Requires-Dist: aiohttp
Requires-Dist: apscheduler
